{"expires":1731425918499,"value":{"code":200,"headers":{"etag":"W/\"Rug6byC972\"","last-modified":"Tue, 05 Nov 2024 15:38:38 GMT","cache-control":"s-maxage=604800, stale-while-revalidate"},"body":{"prefix":"fluent","lastModified":1730307156,"aliases":{},"width":20,"height":20,"icons":{"road-24-regular":{"body":"<path fill=\"currentColor\" d=\"M5.5 2.75a.75.75 0 0 0-1.5 0v18.5a.75.75 0 0 0 1.5 0zm14.5 0a.75.75 0 0 0-1.5 0v18.5a.75.75 0 0 0 1.5 0zm-7.25 0a.75.75 0 0 0-1.5 0v3.5a.75.75 0 0 0 1.5 0zm-1.5 11a.75.75 0 0 0 1.5 0v-3.5a.75.75 0 0 0-1.5 0zm0 4a.75.75 0 0 1 1.5 0v3.5a.75.75 0 0 1-1.5 0z\"/>","width":24,"height":24}}}},"mtime":1730821118739,"integrity":"i1DF1I36Bf"}